laplace_bayesopt/__init__.py
laplace_bayesopt/acqf.py
laplace_bayesopt/botorch.py
laplace_bayesopt-0.1.7.dist-info/METADATA
laplace_bayesopt-0.1.7.dist-info/WHEEL
laplace_bayesopt-0.1.7.dist-info/RECORD
