Metadata-Version: 2.3
Name: laplace-bayesopt
Version: 0.1.7
Summary: Bayesian optimization interface for the laplace-torch library
Author-email: Agustinus Kristiadi <agustinus@kristia.de>
License: MIT
Classifier: Development Status :: 3 - Alpha
Classifier: License :: OSI Approved :: MIT License
Classifier: Operating System :: OS Independent
Classifier: Programming Language :: Python :: 3
Requires-Python: >=3.9
Requires-Dist: botorch>=0.10.0
Requires-Dist: laplace-torch>=0.2.1
Requires-Dist: pandas>=2.2.2
Requires-Dist: torch>=2.0
